forkscout/__init__.py
forkscout/cli.py
forkscout/exceptions.py
forkscout/ai/__init__.py
forkscout/ai/client.py
forkscout/ai/display_formatter.py
forkscout/ai/error_handler.py
forkscout/ai/summary_engine.py
forkscout/analysis/__init__.py
forkscout/analysis/code_quality_analyzer.py
forkscout/analysis/commit_categorizer.py
forkscout/analysis/commit_explanation_engine.py
forkscout/analysis/commit_status_classifier.py
forkscout/analysis/commit_verification_engine.py
forkscout/analysis/documentation_analyzer.py
forkscout/analysis/documentation_report_generator.py
forkscout/analysis/explanation_formatter.py
forkscout/analysis/explanation_generator.py
forkscout/analysis/fork_commit_status_checker.py
forkscout/analysis/fork_data_collection_engine.py
forkscout/analysis/fork_discovery.py
forkscout/analysis/fork_qualification_lookup.py
forkscout/analysis/github_link_generator.py
forkscout/analysis/impact_assessor.py
forkscout/analysis/interactive_analyzer.py
forkscout/analysis/interactive_orchestrator.py
forkscout/analysis/interactive_step.py
forkscout/analysis/interactive_steps.py
forkscout/analysis/kiro_contribution_statistics.py
forkscout/analysis/kiro_usage_documenter.py
forkscout/analysis/optimization_recommender.py
forkscout/analysis/optimization_report_generator.py
forkscout/analysis/override_control.py
forkscout/analysis/project_health_report_generator.py
forkscout/analysis/quality_cli.py
forkscout/analysis/quality_report_generator.py
forkscout/analysis/repository_analyzer.py
forkscout/analysis/simple_table_formatter.py
forkscout/analysis/team_role_documenter.py
forkscout/analysis/test_coverage_analyzer.py
forkscout/analysis/test_coverage_report_generator.py
forkscout/analysis/timestamp_analyzer.py
forkscout/config/__init__.py
forkscout/config/settings.py
forkscout/display/__init__.py
forkscout/display/detailed_commit_display.py
forkscout/display/environment_detector.py
forkscout/display/interaction_mode.py
forkscout/display/progress_reporter.py
forkscout-1.0.5.dist-info/METADATA
forkscout-1.0.5.dist-info/WHEEL
forkscout-1.0.5.dist-info/entry_points.txt
forkscout-1.0.5.dist-info/licenses/LICENSE
forkscout-1.0.5.dist-info/RECORD
