Metadata-Version: 2.4
Name: forkscout
Version: 1.0.5
Summary: Forkscout: Powerful GitHub repository fork analysis tool that discovers valuable features across forks, ranks them by impact, and can create pull requests to integrate improvements back to upstream projects
Project-URL: Homepage, https://github.com/Romamo/forkscout
Project-URL: Repository, https://github.com/Romamo/forkscout
Project-URL: Documentation, https://github.com/Romamo/forkscout#readme
Project-URL: Issues, https://github.com/Romamo/forkscout/issues
Project-URL: Changelog, https://github.com/Romamo/forkscout/releases
Project-URL: Bug Reports, https://github.com/Romamo/forkscout/issues
Project-URL: Feature Requests, https://github.com/Romamo/forkscout/issues
Project-URL: Source Code, https://github.com/Romamo/forkscout
Author-email: Roman Medvedev <pypi@romavm.dev>
Maintainer-email: Roman Medvedev <pypi@romavm.dev>
License: MIT License
License-File: LICENSE
Keywords: analysis,automation,code-analysis,code-quality,collaboration,developer-tools,feature-discovery,fork,git,github,open-source,productivity,pull-request,repository,workflow
Classifier: Development Status :: 5 - Production/Stable
Classifier: Environment :: Console
Classifier: Intended Audience :: Developers
Classifier: Intended Audience :: System Administrators
Classifier: License :: OSI Approved :: MIT License
Classifier: Natural Language :: English
Classifier: Operating System :: OS Independent
Classifier: Programming Language :: Python :: 3
Classifier: Programming Language :: Python :: 3 :: Only
Classifier: Programming Language :: Python :: 3.12
Classifier: Topic :: Software Development :: Libraries :: Python Modules
Classifier: Topic :: Software Development :: Quality Assurance
Classifier: Topic :: Software Development :: Version Control :: Git
Classifier: Topic :: System :: Systems Administration
Classifier: Topic :: Utilities
Classifier: Typing :: Typed
Requires-Python: >=3.12
Requires-Dist: aiohttp>=3.12.15
Requires-Dist: aiosqlite>=0.19.0
Requires-Dist: asyncio-throttle>=1.0.2
Requires-Dist: click>=8.1.0
Requires-Dist: gitpython>=3.1.45
Requires-Dist: httpx>=0.25.0
Requires-Dist: openai>=1.101.0
Requires-Dist: pydantic-settings>=2.1.0
Requires-Dist: pydantic>=2.5.0
Requires-Dist: pyyaml>=6.0.0
Requires-Dist: rich>=13.7.0
Provides-Extra: dev
Requires-Dist: black>=23.12.0; extra == 'dev'
Requires-Dist: mypy>=1.8.0; extra == 'dev'
Requires-Dist: pre-commit>=3.6.0; extra == 'dev'
Requires-Dist: psutil>=5.9.0; extra == 'dev'
Requires-Dist: pytest-asyncio>=0.21.0; extra == 'dev'
Requires-Dist: pytest-cov>=4.1.0; extra == 'dev'
Requires-Dist: pytest-mock>=3.12.0; extra == 'dev'
Requires-Dist: pytest-timeout>=2.1.0; extra == 'dev'
Requires-Dist: pytest>=7.4.0; extra == 'dev'
Requires-Dist: respx>=0.20.0; extra == 'dev'
Requires-Dist: ruff>=0.1.8; extra == 'dev'
